alvin_api_client/__init__.py
alvin_api_client/api_client.py
alvin_api_client/configuration.py
alvin_api_client/exceptions.py
alvin_api_client/model_utils.py
alvin_api_client/rest.py
alvin_api_client/api/__init__.py
alvin_api_client/api/default_api.py
alvin_api_client/apis/__init__.py
alvin_api_client/model/__init__.py
alvin_api_client/model/accept_invite_request.py
alvin_api_client/model/admin_config.py
alvin_api_client/model/aggregated_search_cost.py
alvin_api_client/model/aggregated_search_orchestration_info.py
alvin_api_client/model/airflow_additional_config.py
alvin_api_client/model/alter_parse_result.py
alvin_api_client/model/alter_type.py
alvin_api_client/model/alvin_description_request.py
alvin_api_client/model/api_key_scope.py
alvin_api_client/model/api_key_status.py
alvin_api_client/model/api_keys_response.py
alvin_api_client/model/app_api_lineage_models_entity_graph_connector_edge.py
alvin_api_client/model/app_api_lineage_models_entity_graph_node.py
alvin_api_client/model/app_notifications_models_event_type.py
alvin_api_client/model/app_schemas_core_data_entity_lineage_entity_graph_connector_edge.py
alvin_api_client/model/app_schemas_core_data_entity_lineage_entity_graph_node.py
alvin_api_client/model/app_schemas_core_data_platform_events_event_type.py
alvin_api_client/model/app_schemas_impact_analysis_response_impact_analysis_query_report.py
alvin_api_client/model/app_schemas_impact_analysis_response_impact_analysis_response.py
alvin_api_client/model/app_schemas_impact_analysis_response_impact_analysis_response_status.py
alvin_api_client/model/app_schemas_impact_analysis_v3_response_impact_analysis_query_report.py
alvin_api_client/model/app_schemas_impact_analysis_v3_response_impact_analysis_response.py
alvin_api_client/model/app_schemas_impact_analysis_v3_response_impact_analysis_response_status.py
alvin_api_client/model/auth_provider.py
alvin_api_client/model/bi_platform.py
alvin_api_client/model/big_query_account_details.py
alvin_api_client-1.4.1.dist-info/LICENSE
alvin_api_client-1.4.1.dist-info/METADATA
alvin_api_client-1.4.1.dist-info/WHEEL
alvin_api_client-1.4.1.dist-info/top_level.txt
alvin_api_client-1.4.1.dist-info/RECORD
