Metadata-Version: 2.1
Name: alvin-api-client
Version: 1.4.1
Summary: Python SDK implementing a Client of the Alvin API
Home-page: https://github.com/alvindotai/alvin/tree/master/alvin_api_client
Author: Alvin
Author-email: tech@alvin.ai
License: AGPLv3
Project-URL: Bug Tracker, https://github.com/alvindotai/alvin/issues
Project-URL: Source Code, https://github.com/alvindotai/alvin/tree/master/alvin_api_client
Keywords: alvin api client,python library
Platform: All
Classifier: Development Status :: 5 - Production/Stable
Classifier: Intended Audience :: Developers
Classifier: Intended Audience :: End Users/Desktop
Classifier: License :: OSI Approved :: GNU Affero General Public License v3
Classifier: Natural Language :: English
Classifier: Operating System :: Unix
Classifier: Programming Language :: Python
Classifier: Programming Language :: Python :: 3 :: Only
Classifier: Programming Language :: Python :: 3.6
Classifier: Programming Language :: Python :: 3.7
Classifier: Programming Language :: Python :: 3.8
Classifier: Programming Language :: Python :: 3.9
Classifier: Programming Language :: Python :: 3.10
Classifier: Topic :: Scientific/Engineering
Classifier: Topic :: Software Development
Classifier: Topic :: Software Development :: Libraries :: Python Modules
Classifier: Topic :: System :: Software Distribution
Classifier: Topic :: Utilities
Requires-Python: >=3.6
License-File: LICENSE
Requires-Dist: urllib3 (>=1.25.3)
Requires-Dist: python-dateutil
